<?xml version="1.0"?>
<tetrisFill>
	<problem>
		<grid row="22" col="62">0 0 0 0 0 0 0 0 0 0 0 0 0 0 0 0 0 0 0 0 0 0 0 0 0 0 0 0 0 0 0 0 0 0 0 0 0 0 0 0 0 0 0 0 0 0 0 0 0 0 0 0 0 0 0 0 0 0 0 0 0 0 0 0 1 1 0 0 0 0 0 0 0 0 0 0 1 0 0 0 0 0 0 0 0 0 0 0 0 0 0 0 0 0 0 0 0 0 0 0 0 0 0 0 0 0 0 0 0 0 0 0 0 0 0 0 0 0 0 0 0 0 0 0 0 0 1 1 0 0 0 0 0 0 0 0 0 1 1 0 0 0 0 0 0 0 0 0 0 0 0 0 0 0 0 0 0 0 0 0 0 0 0 0 1 1 1 0 0 0 0 0 0 0 0 0 0 0 0 0 0 0 0 0 0 0 0 0 1 1 1 0 0 0 0 0 0 0 1 1 1 1 0 0 0 0 0 0 0 0 0 0 0 0 0 0 0 0 0 0 0 0 0 0 0 1 1 1 1 1 0 0 0 0 0 0 0 0 0 0 0 0 0 0 0 0 0 0 0 0 0 1 1 0 0 0 0 0 0 1 1 1 1 1 0 0 0 0 0 0 0 0 0 0 0 0 0 0 0 0 0 0 0 0 0 0 1 1 1 1 1 1 1 0 0 0 0 0 0 0 0 0 0 0 0 0 0 0 0 0 0 0 0 1 1 1 0 0 0 0 1 1 1 1 1 1 0 0 0 0 0 0 0 0 0 0 0 0 0 0 0 0 0 0 0 0 0 0 1 1 0 0 0 1 1 0 0 0 0 0 0 0 0 0 0 0 0 0 0 0 0 0 0 0 0 1 1 1 0 0 0 0 1 1 1 0 1 1 0 0 0 0 0 0 0 0 0 0 0 0 0 0 0 0 0 0 0 0 0 1 1 0 0 0 0 1 1 0 0 0 0 0 0 0 0 0 0 0 0 0 0 0 0 0 0 0 0 1 1 1 1 0 0 1 1 1 0 0 1 1 0 0 0 0 0 0 0 0 0 0 0 0 0 0 0 0 0 0 1 1 0 1 1 0 0 0 0 1 1 0 0 0 0 0 0 0 0 0 0 0 0 0 0 0 0 0 0 0 0 0 1 1 1 1 0 1 1 0 0 0 1 1 0 0 0 0 0 0 1 1 1 1 0 0 1 1 0 0 1 1 1 1 0 1 1 0 0 0 0 1 1 0 0 0 0 0 0 0 0 0 0 0 0 0 0 0 0 0 0 0 0 0 1 1 1 1 1 1 1 0 0 1 1 1 0 0 0 0 0 1 1 1 1 1 1 0 1 1 1 1 1 1 1 1 0 0 1 1 0 0 0 1 1 0 0 0 0 0 0 0 0 1 0 0 0 1 1 1 1 0 0 0 0 0 1 1 0 1 1 1 0 0 0 1 1 0 0 0 0 0 1 1 1 1 1 1 1 0 1 1 1 1 1 0 0 1 0 0 1 1 0 0 1 1 0 0 0 0 0 0 0 0 0 1 1 0 1 1 0 1 1 0 0 0 0 0 1 1 0 0 1 1 0 0 0 1 1 0 0 0 0 1 1 1 0 0 0 1 1 0 0 1 1 0 0 0 1 1 0 0 1 1 1 1 1 1 0 0 0 0 1 1 0 0 0 1 1 1 1 0 0 1 1 0 0 0 0 0 1 1 0 0 0 0 0 0 1 1 1 0 0 0 1 1 1 0 0 0 0 1 1 0 0 1 1 0 0 0 1 1 0 0 1 1 1 1 1 0 0 0 0 0 1 1 0 0 0 1 1 1 0 0 0 1 0 0 0 0 0 0 1 1 0 0 0 0 0 0 1 1 1 0 0 0 1 1 1 0 0 0 1 1 1 0 0 1 1 0 0 0 1 1 0 0 0 1 1 1 0 0 0 0 0 1 1 1 0 0 0 1 1 1 0 0 1 1 0 0 0 0 0 0 1 1 0 0 0 0 0 0 1 1 1 0 0 1 1 1 0 0 0 1 1 1 1 0 0 1 1 0 0 1 1 1 0 0 0 1 1 1 0 0 0 0 0 1 1 1 0 0 0 1 1 1 0 0 1 1 0 0 0 0 0 0 1 1 0 0 0 0 0 0 1 1 1 1 1 1 1 0 0 0 0 1 1 1 1 0 0 1 1 0 0 1 1 0 0 0 1 1 1 1 1 0 0 0 0 1 1 1 0 0 1 1 1 1 0 0 1 1 0 0 0 0 0 1 1 0 0 0 0 0 0 0 1 1 1 1 1 1 1 0 0 0 1 1 1 1 1 1 1 1 1 0 0 1 1 0 0 1 1 1 0 1 1 0 0 0 0 1 1 1 0 0 1 1 1 1 0 0 1 1 0 0 0 0 0 1 1 0 0 0 0 0 0 0 1 1 1 1 1 1 1 1 1 1 1 0 0 1 1 1 1 1 0 0 0 1 0 0 1 1 1 0 0 1 1 1 0 0 1 1 1 1 1 1 1 0 1 1 0 0 1 1 1 0 0 0 1 1 1 0 0 0 0 0 0 0 0 1 1 1 1 0 0 1 1 1 0 0 0 0 1 1 1 0 0 0 0 1 1 1 1 1 0 0 0 0 1 1 1 1 1 1 0 1 1 1 1 0 1 1 0 0 1 1 1 0 0 0 1 1 0 0 0 0 0 0 0 0 0 1 1 1 0 0 0 0 0 0 0 0 0 0 0 0 0 0 0 0 0 1 1 1 1 1 0 0 0 0 0 1 1 1 1 0 0 0 1 1 0 0 0 1 0 0 0 1 1 0 0 0 0 0 0 0 0 0 0 0 0 0 0 0 0 0 0 0 0 0 0 0 0 0 0 0 0 0 0 0 0 0 0 0 0 0 0 0 0 0 0 0 0 0 0 1 0 0 0 0 0 0 0 0 0 0 0 0 0 0 0 0 0 0 0 0 0 0 0 0 0 0 0 0 0 0 0 0 0 0 0 0 0 0 0 0 0 0 0 0 0 0 0 0 0 0 0 0 0 0 0 0 0 0 0 0 0 0 0 0 0 0 0 0 0 0 0 0 0 0 0 0 0 0</grid>
		<start row="0" col="0" />
		<seed>4</seed>
	</problem>
	<solution>
		<piece type="0" row="0" col="22" />
		<piece type="3" row="0" col="23" />
		<piece type="3" row="0" col="26" />
		<piece type="14" row="2" col="29" />
		<piece type="15" row="1" col="27" />
		<piece type="8" row="1" col="28" />
		<piece type="17" row="0" col="29" />
		<piece type="1" row="0" col="31" />
		<piece type="17" row="0" col="41" />
		<piece type="17" row="0" col="37" />
		<piece type="9" row="2" col="35" />
		<piece type="18" row="0" col="35" />
		<piece type="16" row="0" col="34" />
		<piece type="3" row="5" col="28" />
		<piece type="14" row="5" col="30" />
		<piece type="9" row="3" col="33" />
		<piece type="6" row="2" col="32" />
		<piece type="1" row="3" col="29" />
		<piece type="10" row="3" col="26" />
		<piece type="15" row="1" col="25" />
		<piece type="16" row="1" col="24" />
		<piece type="0" row="3" col="25" />
		<piece type="18" row="5" col="21" />
		<piece type="12" row="4" col="22" />
		<piece type="10" row="3" col="19" />
		<piece type="7" row="2" col="21" />
		<piece type="12" row="1" col="18" />
		<piece type="18" row="0" col="20" />
		<piece type="15" row="3" col="7" />
		<piece type="9" row="3" col="9" />
		<piece type="6" row="6" col="8" />
		<piece type="11" row="5" col="6" />
		<piece type="15" row="3" col="5" />
		<piece type="6" row="0" col="4" />
		<piece type="15" row="1" col="5" />
		<piece type="3" row="0" col="6" />
		<piece type="17" row="0" col="9" />
		<piece type="3" row="1" col="7" />
		<piece type="3" row="2" col="8" />
		<piece type="14" row="2" col="10" />
		<piece type="17" row="1" col="10" />
		<piece type="5" row="0" col="13" />
		<piece type="17" row="0" col="16" />
		<piece type="9" row="8" col="16" />
		<piece type="0" row="12" col="15" />
		<piece type="15" row="10" col="15" />
		<piece type="4" row="11" col="16" />
		<piece type="8" row="10" col="17" />
		<piece type="14" row="8" col="19" />
		<piece type="8" row="8" col="17" />
		<piece type="1" row="6" col="17" />
		<piece type="16" row="4" col="16" />
		<piece type="11" row="1" col="15" />
		<piece type="9" row="1" col="17" />
		<piece type="14" row="3" col="17" />
		<piece type="18" row="5" col="17" />
		<piece type="2" row="5" col="19" />
		<piece type="17" row="7" col="21" />
		<piece type="5" row="6" col="23" />
		<piece type="13" row="5" col="26" />
		<piece type="16" row="11" col="28" />
		<piece type="0" row="13" col="27" />
		<piece type="16" row="9" col="27" />
		<piece type="14" row="7" col="26" />
		<piece type="15" row="6" col="29" />
		<piece type="13" row="6" col="31" />
		<piece type="3" row="6" col="33" />
		<piece type="14" row="16" col="34" />
		<piece type="10" row="14" col="35" />
		<piece type="18" row="13" col="37" />
		<piece type="16" row="10" col="36" />
		<piece type="16" row="9" col="37" />
		<piece type="16" row="6" col="36" />
		<piece type="1" row="4" col="34" />
		<piece type="6" row="3" col="37" />
		<piece type="17" row="2" col="36" />
		<piece type="17" row="1" col="37" />
		<piece type="5" row="1" col="41" />
		<piece type="18" row="15" col="50" />
		<piece type="4" row="12" col="51" />
		<piece type="6" row="11" col="51" />
		<piece type="16" row="11" col="50" />
		<piece type="17" row="10" col="49" />
		<piece type="3" row="9" col="48" />
		<piece type="16" row="8" col="47" />
		<piece type="2" row="14" col="42" />
		<piece type="18" row="16" col="44" />
		<piece type="18" row="13" col="45" />
		<piece type="5" row="15" col="44" />
		<piece type="5" row="13" col="42" />
		<piece type="4" row="10" col="43" />
		<piece type="16" row="9" col="45" />
		<piece type="0" row="10" col="46" />
		<piece type="11" row="7" col="45" />
		<piece type="13" row="5" col="45" />
		<piece type="13" row="3" col="45" />
		<piece type="0" row="1" col="44" />
		<piece type="0" row="0" col="45" />
		<piece type="14" row="0" col="55" />
		<piece type="17" row="0" col="52" />
		<piece type="14" row="1" col="52" />
		<piece type="4" row="1" col="49" />
		<piece type="12" row="0" col="50" />
		<piece type="17" row="0" col="46" />
		<piece type="17" row="1" col="46" />
		<piece type="18" row="5" col="48" />
		<piece type="6" row="2" col="48" />
		<piece type="16" row="2" col="47" />
		<piece type="15" row="6" col="47" />
		<piece type="7" row="7" col="49" />
		<piece type="14" row="8" col="51" />
		<piece type="5" row="7" col="52" />
		<piece type="8" row="9" col="54" />
		<piece type="12" row="3" col="55" />
		<piece type="1" row="4" col="57" />
		<piece type="2" row="5" col="55" />
		<piece type="0" row="6" col="57" />
		<piece type="0" row="6" col="55" />
		<piece type="1" row="4" col="51" />
		<piece type="1" row="5" col="52" />
		<piece type="18" row="6" col="50" />
		<piece type="8" row="4" col="49" />
		<piece type="15" row="2" col="51" />
		<piece type="12" row="3" col="53" />
		<piece type="17" row="2" col="54" />
		<piece type="10" row="0" col="57" />
		<piece type="5" row="0" col="59" />
		<piece type="10" row="1" col="59" />
		<piece type="11" row="2" col="57" />
		<piece type="16" row="4" col="61" />
		<piece type="8" row="3" col="59" />
		<piece type="1" row="5" col="58" />
		<piece type="8" row="7" col="58" />
		<piece type="2" row="8" col="60" />
		<piece type="11" row="11" col="60" />
		<piece type="16" row="13" col="60" />
		<piece type="16" row="14" col="61" />
		<piece type="16" row="18" col="61" />
		<piece type="17" row="21" col="57" />
		<piece type="17" row="20" col="57" />
		<piece type="11" row="10" col="57" />
		<piece type="6" row="12" col="56" />
		<piece type="16" row="13" col="57" />
		<piece type="0" row="17" col="57" />
		<piece type="16" row="15" col="56" />
		<piece type="4" row="19" col="55" />
		<piece type="4" row="17" col="52" />
		<piece type="9" row="19" col="54" />
		<piece type="17" row="21" col="49" />
		<piece type="5" row="20" col="51" />
		<piece type="3" row="20" col="48" />
		<piece type="10" row="18" col="47" />
		<piece type="18" row="20" col="46" />
		<piece type="10" row="20" col="43" />
		<piece type="10" row="19" col="41" />
		<piece type="18" row="18" col="40" />
		<piece type="13" row="16" col="39" />
		<piece type="15" row="18" col="38" />
		<piece type="7" row="20" col="40" />
		<piece type="17" row="21" col="36" />
		<piece type="17" row="20" col="35" />
		<piece type="14" row="20" col="27" />
		<piece type="1" row="20" col="29" />
		<piece type="17" row="21" col="32" />
		<piece type="7" row="19" col="32" />
		<piece type="18" row="11" col="31" />
		<piece type="6" row="10" col="33" />
		<piece type="8" row="13" col="31" />
		<piece type="16" row="15" col="32" />
		<piece type="16" row="14" col="31" />
		<piece type="10" row="17" col="29" />
		<piece type="8" row="19" col="29" />
		<piece type="8" row="19" col="26" />
		<piece type="17" row="21" col="20" />
		<piece type="1" row="20" col="24" />
		<piece type="18" row="19" col="24" />
		<piece type="12" row="17" col="23" />
		<piece type="14" row="18" col="21" />
		<piece type="1" row="19" col="21" />
		<piece type="18" row="19" col="19" />
		<piece type="7" row="20" col="17" />
		<piece type="2" row="18" col="17" />
		<piece type="6" row="19" col="16" />
		<piece type="15" row="19" col="7" />
		<piece type="12" row="18" col="7" />
		<piece type="12" row="18" col="9" />
		<piece type="18" row="20" col="9" />
		<piece type="17" row="21" col="11" />
		<piece type="5" row="20" col="13" />
		<piece type="4" row="18" col="11" />
		<piece type="11" row="6" col="12" />
		<piece type="6" row="8" col="11" />
		<piece type="4" row="9" col="11" />
		<piece type="16" row="12" col="11" />
		<piece type="4" row="10" col="9" />
		<piece type="2" row="14" col="7" />
		<piece type="6" row="13" col="6" />
		<piece type="9" row="10" col="6" />
		<piece type="12" row="12" col="7" />
		<piece type="13" row="13" col="9" />
		<piece type="10" row="15" col="9" />
		<piece type="5" row="17" col="9" />
		<piece type="0" row="15" col="7" />
		<piece type="16" row="16" col="5" />
		<piece type="16" row="16" col="6" />
		<piece type="10" row="20" col="5" />
		<piece type="9" row="19" col="4" />
		<piece type="18" row="20" col="2" />
		<piece type="18" row="20" col="0" />
		<piece type="16" row="12" col="0" />
		<piece type="16" row="16" col="0" />
		<piece type="16" row="16" col="1" />
		<piece type="6" row="15" col="2" />
		<piece type="3" row="14" col="1" />
		<piece type="16" row="8" col="3" />
		<piece type="15" row="11" col="2" />
		<piece type="0" row="11" col="1" />
		<piece type="13" row="9" col="0" />
		<piece type="16" row="4" col="0" />
		<piece type="13" row="7" col="0" />
		<piece type="16" row="7" col="2" />
		<piece type="18" row="5" col="1" />
		<piece type="0" row="2" col="1" />
		<piece type="6" row="1" col="0" />
		<piece type="17" row="0" col="0" />
	</solution>
</tetrisFill>
